ai_chat_bot/__init__.py
ai_chat_bot/config.py
ai_chat_bot/main.py
ai_chat_bot/clients/__init__.py
ai_chat_bot/clients/gemini.py
ai_chat_bot/models/__init__.py
ai_chat_bot/models/messages.py
ai_chat_bot/ui/__init__.py
ai_chat_bot/ui/display.py
ai_chat_bot/utils/__init__.py
ai_chat_bot/utils/exceptions.py
chat_bot_cli_mexo-0.1.0.dist-info/licenses/LICENSE
chat_bot_cli_mexo-0.1.0.dist-info/METADATA
chat_bot_cli_mexo-0.1.0.dist-info/WHEEL
chat_bot_cli_mexo-0.1.0.dist-info/entry_points.txt
chat_bot_cli_mexo-0.1.0.dist-info/top_level.txt
chat_bot_cli_mexo-0.1.0.dist-info/RECORD
