Metadata-Version: 2.4
Name: chat-bot-cli-mexo
Version: 0.1.0
Summary: Add your description here
Author-email: Sajal <thehackertimes2k23@gmail.com>
License: MIT
Keywords: ai,chatbot,gemini,cli,llm,streaming
Classifier: Development Status :: 4 - Beta
Classifier: Environment :: Console
Classifier: Intended Audience :: Developers
Classifier: License :: OSI Approved :: MIT License
Classifier: Programming Language :: Python :: 3
Classifier: Programming Language :: Python :: 3.11
Classifier: Programming Language :: Python :: 3.12
Classifier: Topic :: Scientific/Engineering :: Artificial Intelligence
Requires-Python: >=3.12
License-File: LICENSE
Requires-Dist: httpx>=0.28.1
Requires-Dist: pydantic>=2.12.5
Requires-Dist: pydantic-settings>=2.12.0
Requires-Dist: rich>=14.2.0
Dynamic: license-file
